LICENSE
MANIFEST.in
README.md
requirements.txt
setup.py
src/mime/__init__.py
src/mime/__version__.py
src/mime/spec/__init__.py
src/mime/tools/__init__.py
src/mime/tools/specxmlparser.py
src/pymime.egg-info/PKG-INFO
src/pymime.egg-info/SOURCES.txt
src/pymime.egg-info/dependency_links.txt
src/pymime.egg-info/requires.txt
src/pymime.egg-info/top_level.txt