Metadata-Version: 1.1
Name: pymime
Version: 0.1.1
Summary: Mime types spec and tools
Home-page: https://github.com/lipixun/pymime
Author: lipixun
Author-email: lipixun@outlook.com
License: LICENSE
Keywords: python,mimetypes,mime
Platform: UNKNOWN
Classifier: Development Status :: 5 - Production/Stable
Classifier: License :: OSI Approved :: GNU General Public License v2 (GPLv2)
Classifier: Intended Audience :: Developers
Classifier: Operating System :: POSIX
Classifier: Topic :: Internet
Classifier: Topic :: Software Development :: Libraries
Classifier: Topic :: Software Development :: Libraries :: Python Modules
Classifier: Programming Language :: Python
Classifier: Programming Language :: Python :: 2.7
